neuronmix/__init__.py
neuronmix-0.1.3.dist-info/licenses/LICENSE
neuronmix-0.1.3.dist-info/METADATA
neuronmix-0.1.3.dist-info/WHEEL
neuronmix-0.1.3.dist-info/top_level.txt
neuronmix-0.1.3.dist-info/RECORD
