Metadata-Version: 2.4
Name: neuronmix
Version: 0.1.3
Summary: Neuron-level mixed activation layer for PyTorch
Home-page: https://github.com/ajaviaad/neuronmix
Author: Muhammad Adeel Javaid
Author-email: ajavaid@ieee.org
License: MIT
Project-URL: Documentation, https://github.com/ajaviaad/neuronmix
Project-URL: Source, https://github.com/ajaviaad/neuronmix
Project-URL: Tracker, https://github.com/ajaviaad/neuronmix/issues
Classifier: Programming Language :: Python :: 3
Classifier: License :: OSI Approved :: MIT License
Classifier: Operating System :: OS Independent
Requires-Python: >=3.6
License-File: LICENSE
Requires-Dist: torch
Dynamic: author
Dynamic: author-email
Dynamic: classifier
Dynamic: description
Dynamic: description-content-type
Dynamic: home-page
Dynamic: license
Dynamic: license-file
Dynamic: project-url
Dynamic: requires-dist
Dynamic: requires-python
Dynamic: summary
